odoo/addons/l10n_it_esigibilita_iva/README.rst
odoo/addons/l10n_it_esigibilita_iva/__init__.py
odoo/addons/l10n_it_esigibilita_iva/__manifest__.py
odoo/addons/l10n_it_esigibilita_iva/i18n/es_AR.po
odoo/addons/l10n_it_esigibilita_iva/i18n/it.po
odoo/addons/l10n_it_esigibilita_iva/i18n/l10n_it_esigibilita_iva.pot
odoo/addons/l10n_it_esigibilita_iva/models/__init__.py
odoo/addons/l10n_it_esigibilita_iva/models/account.py
odoo/addons/l10n_it_esigibilita_iva/readme/CONTRIBUTORS.rst
odoo/addons/l10n_it_esigibilita_iva/readme/DESCRIPTION.rst
odoo/addons/l10n_it_esigibilita_iva/static/description/icon.png
odoo/addons/l10n_it_esigibilita_iva/static/description/index.html
odoo/addons/l10n_it_esigibilita_iva/views/account_view.xml
odoo12_addon_l10n_it_esigibilita_iva-12.0.2.0.0.dist-info/METADATA
odoo12_addon_l10n_it_esigibilita_iva-12.0.2.0.0.dist-info/WHEEL
odoo12_addon_l10n_it_esigibilita_iva-12.0.2.0.0.dist-info/top_level.txt
odoo12_addon_l10n_it_esigibilita_iva-12.0.2.0.0.dist-info/RECORD
