Metadata-Version: 2.1
Name: odoo12-addon-l10n-it-esigibilita-iva
Version: 12.0.2.0.0
Summary: Italian Localization - Esigibilita' IVA
Home-page: https://github.com/OCA/l10n-italy
Author: Openforce di Camilli Alessandro, Odoo Community Association (OCA)
Author-email: support@odoo-community.org
License: LGPL-3
Platform: UNKNOWN
Classifier: Programming Language :: Python
Classifier: Framework :: Odoo
Classifier: License :: OSI Approved :: GNU Lesser General Public License v3 (LGPLv3)
Classifier: Development Status :: 4 - Beta
Requires-Python: >=3.5
Requires-Dist: odoo (<12.1dev,>=12.0a)
